cicada_vector/__init__.py
cicada_vector/cigrep.py
cicada_vector/cli.py
cicada_vector/db.py
cicada_vector/hybrid.py
cicada_vector/indexer.py
cicada_vector/keyword_db.py
cicada_vector/mcp.py
cicada_vector/rag.py
cicada_vector-0.1.2.dist-info/METADATA
cicada_vector-0.1.2.dist-info/WHEEL
cicada_vector-0.1.2.dist-info/entry_points.txt
cicada_vector-0.1.2.dist-info/RECORD
