Metadata-Version: 2.4
Name: cicada-vector
Version: 0.1.2
Summary: A poor man's vector database for Python. Zero dependencies, JSONL storage.
Author-email: Cicada Team <wende@hey.com>
Classifier: Development Status :: 3 - Alpha
Classifier: Intended Audience :: Developers
Classifier: License :: OSI Approved :: MIT License
Classifier: Programming Language :: Python :: 3
Requires-Python: >=3.10
Provides-Extra: numpy
Requires-Dist: numpy; extra == 'numpy'
Provides-Extra: server
Requires-Dist: mcp>=0.1.0; extra == 'server'
